RecMaster/__init__.py
RecMaster/audio_only_ui.py
RecMaster/audio_recorder.py
RecMaster/videoRecorder.py
RecMaster-0.1.2.dist-info/METADATA
RecMaster-0.1.2.dist-info/WHEEL
RecMaster-0.1.2.dist-info/entry_points.txt
RecMaster-0.1.2.dist-info/top_level.txt
RecMaster-0.1.2.dist-info/RECORD
