Metadata-Version: 2.1
Name: RecMaster
Version: 0.1.2
Summary: A simple and efficient screen recorder with audio support
Home-page: https://github.com/JimEverest/RecMaster
Author: JimEverest
Author-email: tianwai263@gmail.com
Classifier: Development Status :: 3 - Alpha
Classifier: Intended Audience :: End Users/Desktop
Classifier: Topic :: Multimedia :: Sound/Audio :: Capture/Recording
Classifier: Topic :: Multimedia :: Video :: Capture
Classifier: Programming Language :: Python :: 3
Classifier: License :: OSI Approved :: MIT License
Classifier: Operating System :: Microsoft :: Windows
Requires-Python: >=3.6
Requires-Dist: comtypes
Requires-Dist: numpy
Requires-Dist: pywin32
Requires-Dist: pycaw
Requires-Dist: ffmpeg-python
Requires-Dist: humanize
